__init__.py
quao/__init__.py
quao/async_tasks/__init__.py
quao/async_tasks/async_task.py
quao/async_tasks/export_circuit_task.py
quao/async_tasks/post_processing_task.py
quao/component/__init__.py
quao/component/backend/__init__.py
quao/component/backend/invocation.py
quao/component/backend/job_fetching.py
quao/component/callback/__init__.py
quao/component/callback/update_job_metadata.py
quao/component/device/__init__.py
quao/component/device/device_selection.py
quao/config/__init__.py
quao/config/logging_config.py
quao/config/thread_config.py
quao/data/__init__.py
quao/data/async_task/__init__.py
quao/data/async_task/circuit_export/__init__.py
quao/data/async_task/circuit_export/backend_holder.py
quao/data/async_task/circuit_export/circuit_holder.py
quao/data/backend/__init__.py
quao/data/backend/backend_information.py
quao/data/callback/__init__.py
quao/data/callback/callback_url.py
quao/data/device/__init__.py
quao/data/device/circuit_running_option.py
quao/data/promise/__init__.py
quao/data/promise/post_processing_promise.py
quao/data/promise/promise.py
quao/data/request/__init__.py
quao/data/request/invocation_request.py
quao/data/request/job_fetching_request.py
quao/data/request/request.py
quao/data/response/__init__.py
quao/data/response/authentication.py
quao/data/response/job_response.py
quao/data/response/project_header.py
quao/enum/__init__.py
quao/enum/base_enum.py
quao/enum/http_header.py
quao/enum/invocation_step.py
quao/enum/media_type.py
quao/enum/processing_unit.py
quao/enum/provider_tag.py
quao/enum/sdk.py
quao/enum/token_type.py
quao/enum/status/__init__.py
quao/enum/status/job_status.py
quao/enum/status/status_code.py
quao/factory/__init__.py
quao/factory/device_factory.py
quao/factory/handler_factory.py
quao/factory/provider_factory.py
quao/handler/__init__.py
quao/handler/handler.py
quao/handler/invocation_handler.py
quao/handler/job_fetching_handler.py
quao/model/__init__.py
quao/model/device/__init__.py
quao/model/device/aws_braket_device.py
quao-0.4.14.dist-info/LICENSE
quao-0.4.14.dist-info/METADATA
quao-0.4.14.dist-info/WHEEL
quao-0.4.14.dist-info/top_level.txt
quao-0.4.14.dist-info/RECORD
