Metadata-Version: 2.1
Name: quao
Version: 0.4.14
Summary: Quao Library supporting Quao Platform for Quantum Computing
Author-email: "CITYNOW Co. Ltd. " <corp@citynow.vn>
License: The MIT License (MIT)
Project-URL: Homepage, https://citynow.vn/
Keywords: quao,quantum
Classifier: License :: OSI Approved :: MIT License
Classifier: Programming Language :: Python
Classifier: Programming Language :: Python :: 3
Requires-Python: >=3.7
License-File: LICENSE
Requires-Dist: types-pkg-resources==0.1.3
Requires-Dist: amazon-braket-sdk==1.49.1
Requires-Dist: dwave-samplers==1.1.0
Requires-Dist: dwave-ocean-sdk==6.5.0
Requires-Dist: loguru==0.7.2
Requires-Dist: pyqubo==1.4.0
Requires-Dist: pylatexenc==2.10
Requires-Dist: pytket==1.18.0
Requires-Dist: qiskit==0.44.1
Requires-Dist: qiskit-aer-gpu==0.11.2
Requires-Dist: qiskit-ibm-runtime==0.17.0
Requires-Dist: qiskit-ibm-provider==0.7.3
Requires-Dist: qbraid==0.4.5
Requires-Dist: tytan==0.0.17
Requires-Dist: requests==2.31.0
Requires-Dist: cuda-quantum==0.6.0
Provides-Extra: dev
Requires-Dist: black; extra == "dev"
Requires-Dist: bumpver; extra == "dev"
Requires-Dist: isort; extra == "dev"
Requires-Dist: pip-tools; extra == "dev"
Requires-Dist: pytest; extra == "dev"
